svdiff_pytorch/__init__.py
svdiff_pytorch/layers.py
svdiff_pytorch/pipeline_stable_diffusion_ddim_inversion.py
svdiff_pytorch/utils.py
svdiff_pytorch/diffusers_models/__init__.py
svdiff_pytorch/diffusers_models/attention.py
svdiff_pytorch/diffusers_models/cross_attention.py
svdiff_pytorch/diffusers_models/dual_transformer_2d.py
svdiff_pytorch/diffusers_models/embeddings.py
svdiff_pytorch/diffusers_models/resnet.py
svdiff_pytorch/diffusers_models/transformer_2d.py
svdiff_pytorch/diffusers_models/unet_2d_blocks.py
svdiff_pytorch/diffusers_models/unet_2d_condition.py
svdiff_pytorch/transformers_models_clip/__init__.py
svdiff_pytorch/transformers_models_clip/modeling_clip.py
svdiff_pytorch-0.2.0.dist-info/LICENSE
svdiff_pytorch-0.2.0.dist-info/METADATA
svdiff_pytorch-0.2.0.dist-info/WHEEL
svdiff_pytorch-0.2.0.dist-info/top_level.txt
svdiff_pytorch-0.2.0.dist-info/RECORD
