Metadata-Version: 2.1
Name: svdiff-pytorch
Version: 0.2.0
Summary: Implementation of 'SVDiff: Compact Parameter Space for Diffusion Fine-Tuning'
Home-page: https://github.com/mkshing/svdiff-pytorch
Author: Makoto Shing
License: MIT
License-File: LICENSE
Requires-Dist: diffusers (==0.14.0)
Requires-Dist: accelerate
Requires-Dist: torchvision
Requires-Dist: safetensors
Requires-Dist: transformers (>=4.25.1)
Requires-Dist: ftfy
Requires-Dist: tensorboard
Requires-Dist: Jinja2
Requires-Dist: einops
Requires-Dist: wandb
